[
  {
    "id": "279b3400-82b8-484c-80b3-833962f151ac",
    "userEmail": "basiliskan@gmail.com",
    "title": "Can we work it out",
    "type": "request",
    "lastMessage": "Hello again?",
    "lastActivity": "2025-07-07T03:31:04.044Z",
    "messageCount": 4,
    "createdAt": "2025-07-07T03:27:07.482Z",
    "updatedAt": "2025-07-07T03:31:04.044Z"
  },
  {
    "id": "b942bdff-d275-44cc-b199-14bf23dabba4",
    "userEmail": "basiliskan@gmail.com",
    "title": "Πες μου ποια task είναι In Porgress",
    "type": "ai",
    "lastMessage": "Based on your workspace with 17 tasks and 0 projects, I can help you with:\n\n• Task management and pr...",
    "lastActivity": "2025-07-07T07:55:31.975Z",
    "messageCount": 13,
    "createdAt": "2025-07-07T03:31:26.218Z",
    "updatedAt": "2025-07-07T07:55:31.975Z"
  },
  {
    "id": "d34bbf34-babb-4cab-9cce-9138a8e48056",
    "userEmail": "basiliskan@gmail.com",
    "title": "what tasks do I have in progress?",
    "type": "ai",
    "lastMessage": "You have one task that is currently \"In Progress\": \n\n1. \"Αποξηλώσεις\" - Project: Project TemplatePro...",
    "lastActivity": "2025-07-07T08:19:39.131Z",
    "messageCount": 4,
    "createdAt": "2025-07-07T08:19:17.622Z",
    "updatedAt": "2025-07-07T08:19:39.131Z"
  }
]